data_buckaroo/__init__.py
data_buckaroo/__metadata__.py
data_buckaroo/_exceptions.py
data_buckaroo/athena_query.py
data_buckaroo/s3_base.py
data_buckaroo/s3_object_base.py
data_buckaroo/utils.py
lightframe/__init__.py
lightframe/__metadata__.py
lightframe/_accessors.py
lightframe/frame.py
lightframe/ndarray.py
lightframe/repr.py
lightframe/series.py
lightframe/util.py
data_buckaroo-0.1.1.dist-info/LICENSE
data_buckaroo-0.1.1.dist-info/WHEEL
data_buckaroo-0.1.1.dist-info/METADATA
data_buckaroo-0.1.1.dist-info/RECORD
